{
    "/js/chunks/vendors~AddGem~AddProject~ChallengePanel~ChallengesCreate~Chats~DiaryBoard~FeedForm~ForgotPassword~G~c0e9e135.0f96eedb318d34059374.js": "/js/chunks/vendors~AddGem~AddProject~ChallengePanel~ChallengesCreate~Chats~DiaryBoard~FeedForm~ForgotPassword~G~c0e9e135.0f96eedb318d34059374.js",
    "/js/chunks/vendors~AddGem~CodeBox~CodeEditor~CodeEditorChat.004294767baedca9eef3.js": "/js/chunks/vendors~AddGem~CodeBox~CodeEditor~CodeEditorChat.004294767baedca9eef3.js",
    "/js/chunks/vendors~ChatList~ChatMessages~MoreOptions~ReplyView.6e4cee06f097c81f0f4e.js": "/js/chunks/vendors~ChatList~ChatMessages~MoreOptions~ReplyView.6e4cee06f097c81f0f4e.js",
    "/js/chunks/AudioPlayer.1f0ead5f1cd16867905c.js": "/js/chunks/AudioPlayer.1f0ead5f1cd16867905c.js",
    "/js/chunks/Images.b3d9c5e5ae278891fadd.js": "/js/chunks/Images.b3d9c5e5ae278891fadd.js",
    "/js/chunks/ProfilePage.e7a5172354d783570f4f.js": "/js/chunks/ProfilePage.e7a5172354d783570f4f.js",
    "/js/chunks/VPressEditor.8b585984f0b792b2c93c.js": "/js/chunks/VPressEditor.8b585984f0b792b2c93c.js",
    "/js/chunks/VideoPlayer.5859bc802dcc99ec59ee.js": "/js/chunks/VideoPlayer.5859bc802dcc99ec59ee.js",
    "/js/chunks/vendors~AddGem~DiaryContent.31bcb1aada4fef67341d.js": "/js/chunks/vendors~AddGem~DiaryContent.31bcb1aada4fef67341d.js",
    "/js/chunks/vendors~ChallengesList~Chats.f5d2ef322c03b0cd0f25.js": "/js/chunks/vendors~ChallengesList~Chats.f5d2ef322c03b0cd0f25.js",
    "/js/chunks/vendors~CodeEditor~CodeEditorChat.59dc5a75177d79d2dc1d.js": "/js/chunks/vendors~CodeEditor~CodeEditorChat.59dc5a75177d79d2dc1d.js",
    "/js/chunks/vendors~VPressEditor.d62213c638e69e2a921e.js": "/js/chunks/vendors~VPressEditor.d62213c638e69e2a921e.js",
    "/js/app.js": "/js/app.js",
    "/js/dashboard.js": "/js/dashboard.js",
    "/js/chunks/AddDatabase.b99270d909a20cc4f24a.js": "/js/chunks/AddDatabase.b99270d909a20cc4f24a.js",
    "/js/chunks/AddGem.9828f0813fd142e0e262.js": "/js/chunks/AddGem.9828f0813fd142e0e262.js",
    "/js/chunks/AddNewFile.e32608bf2b161dc43984.js": "/js/chunks/AddNewFile.e32608bf2b161dc43984.js",
    "/js/chunks/AddProject.9fc17209a7f2251c08e1.js": "/js/chunks/AddProject.9fc17209a7f2251c08e1.js",
    "/js/chunks/AddSubChannel.b831539883247b26e09a.js": "/js/chunks/AddSubChannel.b831539883247b26e09a.js",
    "/js/chunks/AddWebroute.ff8e76a29c141dae60c9.js": "/js/chunks/AddWebroute.ff8e76a29c141dae60c9.js",
    "/js/chunks/Board.5f50d81d76e9439dc44b.js": "/js/chunks/Board.5f50d81d76e9439dc44b.js",
    "/js/chunks/Challenge.26c1494a2e9765ab8458.js": "/js/chunks/Challenge.26c1494a2e9765ab8458.js",
    "/js/chunks/ChallengeDescription.c67417c226528343b605.js": "/js/chunks/ChallengeDescription.c67417c226528343b605.js",
    "/js/chunks/ChallengeDiscussions.4a4e7bc336d1387b36f0.js": "/js/chunks/ChallengeDiscussions.4a4e7bc336d1387b36f0.js",
    "/js/chunks/ChallengeJudges.58c534b80782de75c99f.js": "/js/chunks/ChallengeJudges.58c534b80782de75c99f.js",
    "/js/chunks/ChallengeLeaderboard.994bb3ca08540f8a5790.js": "/js/chunks/ChallengeLeaderboard.994bb3ca08540f8a5790.js",
    "/js/chunks/ChallengePanel.744c6e71953ae71f61c2.js": "/js/chunks/ChallengePanel.744c6e71953ae71f61c2.js",
    "/js/chunks/ChallengeResult.91fdfe4697199e95ce9e.js": "/js/chunks/ChallengeResult.91fdfe4697199e95ce9e.js",
    "/js/chunks/ChallengeRules.7978a816a790bb94f010.js": "/js/chunks/ChallengeRules.7978a816a790bb94f010.js",
    "/js/chunks/Challenges.283ff5af5444b5cd0984.js": "/js/chunks/Challenges.283ff5af5444b5cd0984.js",
    "/js/chunks/ChallengesCreate.152052b5649e27c3ad42.js": "/js/chunks/ChallengesCreate.152052b5649e27c3ad42.js",
    "/js/chunks/ChallengesList.cd52dd0ede11ea26b033.js": "/js/chunks/ChallengesList.cd52dd0ede11ea26b033.js",
    "/js/chunks/ChannelEdit.9c88a4b8b3bd640a435d.js": "/js/chunks/ChannelEdit.9c88a4b8b3bd640a435d.js",
    "/js/chunks/ChannelInfo.65b694bb4a4d29020df9.js": "/js/chunks/ChannelInfo.65b694bb4a4d29020df9.js",
    "/js/chunks/ChatBottom.785c132a7ddeba8309b5.js": "/js/chunks/ChatBottom.785c132a7ddeba8309b5.js",
    "/js/chunks/ChatList.97fd2cb63c00eb208ae5.js": "/js/chunks/ChatList.97fd2cb63c00eb208ae5.js",
    "/js/chunks/ChatMessages.6269b04fef7035ad68cb.js": "/js/chunks/ChatMessages.6269b04fef7035ad68cb.js",
    "/js/chunks/ChatShare.b0c1c68859d9a0c490ca.js": "/js/chunks/ChatShare.b0c1c68859d9a0c490ca.js",
    "/js/chunks/ChatTop.9c87bba22c7f67587221.js": "/js/chunks/ChatTop.9c87bba22c7f67587221.js",
    "/js/chunks/Chats.f043117e841451d5236c.js": "/js/chunks/Chats.f043117e841451d5236c.js",
    "/js/chunks/CodeBox.c5b33de54158373009cc.js": "/js/chunks/CodeBox.c5b33de54158373009cc.js",
    "/js/chunks/CodeBox?v=0.53.d7aa0ac6cbe3fb49cc39.js": "/js/chunks/CodeBox?v=0.53.d7aa0ac6cbe3fb49cc39.js",
    "/js/chunks/CodeEditor.a3495b2270e5959c753d.js": "/js/chunks/CodeEditor.a3495b2270e5959c753d.js",
    "/js/chunks/CodeEditorChat.7a1f3fdcde83b4b363ff.js": "/js/chunks/CodeEditorChat.7a1f3fdcde83b4b363ff.js",
    "/js/chunks/CreateChannel.2ac5ef933619baafabfa.js": "/js/chunks/CreateChannel.2ac5ef933619baafabfa.js",
    "/js/chunks/Diary.dd25d90f9833c30951ef.js": "/js/chunks/Diary.dd25d90f9833c30951ef.js",
    "/js/chunks/DiaryBoard.f50cc7f421b332619084.js": "/js/chunks/DiaryBoard.f50cc7f421b332619084.js",
    "/js/chunks/DiaryContent.247e3d7bd03bb67f0c50.js": "/js/chunks/DiaryContent.247e3d7bd03bb67f0c50.js",
    "/js/chunks/DiaryList.8438a7e6176ffed19ad6.js": "/js/chunks/DiaryList.8438a7e6176ffed19ad6.js",
    "/js/chunks/EachProject.878c395fd7a837d32f20.js": "/js/chunks/EachProject.878c395fd7a837d32f20.js",
    "/js/chunks/EditProfile.62da9bd88b85fa178dc8.js": "/js/chunks/EditProfile.62da9bd88b85fa178dc8.js",
    "/js/chunks/FeedForm.2b6e40e4e363c1102217.js": "/js/chunks/FeedForm.2b6e40e4e363c1102217.js",
    "/js/chunks/Feedback.d32ad44b0d42e68bde6e.js": "/js/chunks/Feedback.d32ad44b0d42e68bde6e.js",
    "/js/chunks/ForgotPassword.fd420efb894add0c4628.js": "/js/chunks/ForgotPassword.fd420efb894add0c4628.js",
    "/js/chunks/GetDiary.fd5db57b4c4ba03fe6d7.js": "/js/chunks/GetDiary.fd5db57b4c4ba03fe6d7.js",
    "/js/chunks/Hub.1a658a9f6ef9d253f73f.js": "/js/chunks/Hub.1a658a9f6ef9d253f73f.js",
    "/js/chunks/ImageCropper.b29c05b3adcda2f69575.js": "/js/chunks/ImageCropper.b29c05b3adcda2f69575.js",
    "/js/chunks/ImageCropperMain.19ddab3beb839b8a1780.js": "/js/chunks/ImageCropperMain.19ddab3beb839b8a1780.js",
    "/js/chunks/ImageLoader.2e1757daddc1c9151763.js": "/js/chunks/ImageLoader.2e1757daddc1c9151763.js",
    "/js/chunks/ImageLoader?v=0.10.0d59dc07bbc0cf2ca71e.js": "/js/chunks/ImageLoader?v=0.10.0d59dc07bbc0cf2ca71e.js",
    "/js/chunks/ImageViewer.3c484abe2d5ddb5883f6.js": "/js/chunks/ImageViewer.3c484abe2d5ddb5883f6.js",
    "/js/chunks/Invitation.9beb5718ba06860272d1.js": "/js/chunks/Invitation.9beb5718ba06860272d1.js",
    "/js/chunks/LiveSession.90a289fc8833e36b8bdc.js": "/js/chunks/LiveSession.90a289fc8833e36b8bdc.js",
    "/js/chunks/MoreOptionChat.d3a6399d2bca9dfbb177.js": "/js/chunks/MoreOptionChat.d3a6399d2bca9dfbb177.js",
    "/js/chunks/MoreOptions.e05059fd42e483981752.js": "/js/chunks/MoreOptions.e05059fd42e483981752.js",
    "/js/chunks/MoreOptionsPanel.c220f857c9c5b9af1136.js": "/js/chunks/MoreOptionsPanel.c220f857c9c5b9af1136.js",
    "/js/chunks/MoreOptionsPost.ff9c2df00354766c8f05.js": "/js/chunks/MoreOptionsPost.ff9c2df00354766c8f05.js",
    "/js/chunks/Notifications.2faf8cd340f8709339d8.js": "/js/chunks/Notifications.2faf8cd340f8709339d8.js",
    "/js/chunks/NotificationsList.28d4e8ee7dc9dd3b1cc3.js": "/js/chunks/NotificationsList.28d4e8ee7dc9dd3b1cc3.js",
    "/js/chunks/PanelLoader.f00077dd8e3720c33619.js": "/js/chunks/PanelLoader.f00077dd8e3720c33619.js",
    "/js/chunks/PanelLoaderChallenge.c368ce75c1c0ec24037b.js": "/js/chunks/PanelLoaderChallenge.c368ce75c1c0ec24037b.js",
    "/js/chunks/PanelSettings.221bf86691150121b495.js": "/js/chunks/PanelSettings.221bf86691150121b495.js",
    "/js/chunks/PostView.970a17d589370b0ae8f8.js": "/js/chunks/PostView.970a17d589370b0ae8f8.js",
    "/js/chunks/ProjectGuide.1cfd026acb17b32a35a6.js": "/js/chunks/ProjectGuide.1cfd026acb17b32a35a6.js",
    "/js/chunks/ProjectList.f1b1f9cf5f3da81708e4.js": "/js/chunks/ProjectList.f1b1f9cf5f3da81708e4.js",
    "/js/chunks/ProjectPanel.30dfaa3b403c28e60808.js": "/js/chunks/ProjectPanel.30dfaa3b403c28e60808.js",
    "/js/chunks/ProjectView.c6fb2575181a4fb67ff8.js": "/js/chunks/ProjectView.c6fb2575181a4fb67ff8.js",
    "/js/chunks/Projects.09910620103711f9bec5.js": "/js/chunks/Projects.09910620103711f9bec5.js",
    "/js/chunks/ReplyView.55aecfee5a9cc9ebe096.js": "/js/chunks/ReplyView.55aecfee5a9cc9ebe096.js",
    "/js/chunks/ResetPassword.a8c37c903af8cd65a6c7.js": "/js/chunks/ResetPassword.a8c37c903af8cd65a6c7.js",
    "/js/chunks/ResourceUpload.8f7d1b7748816e5c79bf.js": "/js/chunks/ResourceUpload.8f7d1b7748816e5c79bf.js",
    "/js/chunks/Reward.0ba442c05d29ef45b54f.js": "/js/chunks/Reward.0ba442c05d29ef45b54f.js",
    "/js/chunks/SetUsername.c187ceb4b2d4b94b4c32.js": "/js/chunks/SetUsername.c187ceb4b2d4b94b4c32.js",
    "/js/chunks/Settings.e329975789b4f25f7705.js": "/js/chunks/Settings.e329975789b4f25f7705.js",
    "/js/chunks/SettingsMain.2383f6039598183add41.js": "/js/chunks/SettingsMain.2383f6039598183add41.js",
    "/js/chunks/SideBar.714b568859a236999373.js": "/js/chunks/SideBar.714b568859a236999373.js",
    "/js/chunks/SubChannels.17aa939278453506ebd8.js": "/js/chunks/SubChannels.17aa939278453506ebd8.js",
    "/js/chunks/TopBarBoard.05346423e0d8649a0ecd.js": "/js/chunks/TopBarBoard.05346423e0d8649a0ecd.js",
    "/js/chunks/Wallet.bcb39a448d0e0c73e029.js": "/js/chunks/Wallet.bcb39a448d0e0c73e029.js",
    "/js/chunks/WalletInfo.879241946314a59e7cd9.js": "/js/chunks/WalletInfo.879241946314a59e7cd9.js",
    "/js/chunks/addPage.b2d0a1ea309ac7f6bbe6.js": "/js/chunks/addPage.b2d0a1ea309ac7f6bbe6.js",
    "/js/chunks/imageCropperBoard.195cb82dd56f31f390ab.js": "/js/chunks/imageCropperBoard.195cb82dd56f31f390ab.js",
    "/js/chunks/imageCropperBoardDiary.46206a4a2b4009e63ead.js": "/js/chunks/imageCropperBoardDiary.46206a4a2b4009e63ead.js",
    "/js/chunks/login.f55a4ef8ec4fa77e90ee.js": "/js/chunks/login.f55a4ef8ec4fa77e90ee.js",
    "/js/chunks/panel-side.e35b0e0d0109a7a8573e.js": "/js/chunks/panel-side.e35b0e0d0109a7a8573e.js",
    "/js/chunks/register.c45cdd3ca6fa88a772cc.js": "/js/chunks/register.c45cdd3ca6fa88a772cc.js",
    "/js/chunks/top-bar.f30185c73b3673c3626e.js": "/js/chunks/top-bar.f30185c73b3673c3626e.js",
    "/js/chunks/top-bar-chat.a0aac0a6b0f513d18368.js": "/js/chunks/top-bar-chat.a0aac0a6b0f513d18368.js",
    "/js/chunks/top-bar-profile.a8c27fb4d52c597ce248.js": "/js/chunks/top-bar-profile.a8c27fb4d52c597ce248.js",
    "/js/chunks/vendors~Chats.ffc108afa042d5c17344.js": "/js/chunks/vendors~Chats.ffc108afa042d5c17344.js",
    "/js/chunks/vendors~ImageCropperMain.d033c0d1a0f7570ad1fe.js": "/js/chunks/vendors~ImageCropperMain.d033c0d1a0f7570ad1fe.js",
    "/js/chunks/verify.b0fd4600f4ae6fa85764.js": "/js/chunks/verify.b0fd4600f4ae6fa85764.js"
}
