{
    "/js/dashboard.js": "/js/dashboard.js",
    "/AddDatabase?v=0.24.js": "/AddDatabase?v=0.24.js",
    "/AddNewFile?v=0.34.js": "/AddNewFile?v=0.34.js",
    "/AddProject?v=0.77.js": "/AddProject?v=0.77.js",
    "/AddWebroute?v=0.38.js": "/AddWebroute?v=0.38.js",
    "/AudioPlayer?v=0.20.js": "/AudioPlayer?v=0.20.js",
    "/Board?v=2.90.js": "/Board?v=2.90.js",
    "/ChallengeDescription?v=0.18.js": "/ChallengeDescription?v=0.18.js",
    "/ChallengeDiscussions?v=0.30.js": "/ChallengeDiscussions?v=0.30.js",
    "/ChallengeJudges?v=0.25.js": "/ChallengeJudges?v=0.25.js",
    "/ChallengeLeaderboard?v=0.28.js": "/ChallengeLeaderboard?v=0.28.js",
    "/ChallengePanel?v=1.35.js": "/ChallengePanel?v=1.35.js",
    "/ChallengeRules?v=0.13.js": "/ChallengeRules?v=0.13.js",
    "/Challenges?v=0.55.js": "/Challenges?v=0.55.js",
    "/ChallengesCreate?v=0.63.js": "/ChallengesCreate?v=0.63.js",
    "/ChallengesList?v=0.52.js": "/ChallengesList?v=0.52.js",
    "/ChannelEdit?v=0.18.js": "/ChannelEdit?v=0.18.js",
    "/ChannelInfo?v=0.60.js": "/ChannelInfo?v=0.60.js",
    "/ChatBottom?v=0.53.js": "/ChatBottom?v=0.53.js",
    "/ChatList?v=1.16.js": "/ChatList?v=1.16.js",
    "/ChatMessages?v=1.85.js": "/ChatMessages?v=1.85.js",
    "/ChatTop?v=0.52.js": "/ChatTop?v=0.52.js",
    "/Chats?v=7.07.js": "/Chats?v=7.07.js",
    "/CodeBox?v=0.41.js": "/CodeBox?v=0.41.js",
    "/CodeEditor?v=1.75.js": "/CodeEditor?v=1.75.js",
    "/CodeEditorChat?v=0.23.js": "/CodeEditorChat?v=0.23.js",
    "/ContentBots?v=0.21.js": "/ContentBots?v=0.21.js",
    "/CreateChannel?v=0.21.js": "/CreateChannel?v=0.21.js",
    "/ForgotPassword?v=0.26.js": "/ForgotPassword?v=0.26.js",
    "/Hub?v=4.67.js": "/Hub?v=4.67.js",
    "/ImageLoader?v=0.10.js": "/ImageLoader?v=0.10.js",
    "/ImageViewer?v=0.27.js": "/ImageViewer?v=0.27.js",
    "/Images?v=0.32.js": "/Images?v=0.32.js",
    "/LiveSession?v=0.68.js": "/LiveSession?v=0.68.js",
    "/PanelLoader?v=0.27.js": "/PanelLoader?v=0.27.js",
    "/PanelSettings?v=0.39.js": "/PanelSettings?v=0.39.js",
    "/ProfilePage?v=0.93.js": "/ProfilePage?v=0.93.js",
    "/ProjectList?v=1.96.js": "/ProjectList?v=1.96.js",
    "/ProjectPanel?v=1.93.js": "/ProjectPanel?v=1.93.js",
    "/ProjectView?v=1.05.js": "/ProjectView?v=1.05.js",
    "/Projects?v=0.25.js": "/Projects?v=0.25.js",
    "/ResetPassword?v=1.66.js": "/ResetPassword?v=1.66.js",
    "/ResourceUpload?v=0.25.js": "/ResourceUpload?v=0.25.js",
    "/SetUsername?v=0.25.js": "/SetUsername?v=0.25.js",
    "/SubChannels?v=0.20.js": "/SubChannels?v=0.20.js",
    "/VideoPlayer?v=0.13.js": "/VideoPlayer?v=0.13.js",
    "/addPage?v=1.31.js": "/addPage?v=1.31.js",
    "/login?v=1.02.js": "/login?v=1.02.js",
    "/panel-side?v=0.24.js": "/panel-side?v=0.24.js",
    "/register?v=1.99.js": "/register?v=1.99.js",
    "/top-bar-chat?v=0.17.js": "/top-bar-chat?v=0.17.js",
    "/top-bar?v=0.50.js": "/top-bar?v=0.50.js",
    "/vendors~ChallengesCreate?v=0.63.js": "/vendors~ChallengesCreate?v=0.63.js",
    "/vendors~CodeBox?v=0.41~CodeEditor?v=1.75.js": "/vendors~CodeBox?v=0.41~CodeEditor?v=1.75.js",
    "/vendors~CodeBox?v=0.41~CodeEditor?v=1.75~CodeEditorChat?v=0.23.js": "/vendors~CodeBox?v=0.41~CodeEditor?v=1.75~CodeEditorChat?v=0.23.js",
    "/vendors~VideoPlayer?v=0.13.js": "/vendors~VideoPlayer?v=0.13.js",
    "/verify?v=0.63.js": "/verify?v=0.63.js",
    "/CodeEditorChat?v=0.24.js": "/CodeEditorChat?v=0.24.js",
    "/vendors~CodeBox?v=0.41~CodeEditor?v=1.75~CodeEditorChat?v=0.24.js": "/vendors~CodeBox?v=0.41~CodeEditor?v=1.75~CodeEditorChat?v=0.24.js",
    "/Chats?v=7.08.js": "/Chats?v=7.08.js",
    "/CodeEditorChat?v=0.25.js": "/CodeEditorChat?v=0.25.js",
    "/vendors~CodeBox?v=0.41~CodeEditor?v=1.75~CodeEditorChat?v=0.25.js": "/vendors~CodeBox?v=0.41~CodeEditor?v=1.75~CodeEditorChat?v=0.25.js",
    "/CodeEditorChat?v=0.27.js": "/CodeEditorChat?v=0.27.js",
    "/vendors~CodeBox?v=0.41~CodeEditor?v=1.75~CodeEditorChat?v=0.27.js": "/vendors~CodeBox?v=0.41~CodeEditor?v=1.75~CodeEditorChat?v=0.27.js",
    "/Chats?v=7.09.js": "/Chats?v=7.09.js",
    "/CodeEditorChat?v=0.28.js": "/CodeEditorChat?v=0.28.js",
    "/vendors~CodeBox?v=0.41~CodeEditor?v=1.75~CodeEditorChat?v=0.28.js": "/vendors~CodeBox?v=0.41~CodeEditor?v=1.75~CodeEditorChat?v=0.28.js",
    "/CodeEditor?v=1.76.js": "/CodeEditor?v=1.76.js",
    "/vendors~CodeBox?v=0.41~CodeEditor?v=1.76.js": "/vendors~CodeBox?v=0.41~CodeEditor?v=1.76.js",
    "/vendors~CodeBox?v=0.41~CodeEditor?v=1.76~CodeEditorChat?v=0.28.js": "/vendors~CodeBox?v=0.41~CodeEditor?v=1.76~CodeEditorChat?v=0.28.js",
    "/CodeBox?v=0.42.js": "/CodeBox?v=0.42.js",
    "/vendors~CodeBox?v=0.42~CodeEditor?v=1.76.js": "/vendors~CodeBox?v=0.42~CodeEditor?v=1.76.js",
    "/vendors~CodeBox?v=0.42~CodeEditor?v=1.76~CodeEditorChat?v=0.28.js": "/vendors~CodeBox?v=0.42~CodeEditor?v=1.76~CodeEditorChat?v=0.28.js",
    "/ChatMessages?v=1.86.js": "/ChatMessages?v=1.86.js",
    "/Chats?v=7.10.js": "/Chats?v=7.10.js",
    "/CodeEditor?v=1.77.js": "/CodeEditor?v=1.77.js",
    "/vendors~CodeBox?v=0.42~CodeEditor?v=1.77.js": "/vendors~CodeBox?v=0.42~CodeEditor?v=1.77.js",
    "/vendors~CodeBox?v=0.42~CodeEditor?v=1.77~CodeEditorChat?v=0.28.js": "/vendors~CodeBox?v=0.42~CodeEditor?v=1.77~CodeEditorChat?v=0.28.js",
    "/vendors~CodeEditor?v=1.77.js": "/vendors~CodeEditor?v=1.77.js",
    "/vendors~CodeEditor?v=1.77~CodeEditorChat?v=0.28.js": "/vendors~CodeEditor?v=1.77~CodeEditorChat?v=0.28.js",
    "/CodeBox?v=0.43.js": "/CodeBox?v=0.43.js",
    "/vendors~CodeBox?v=0.43~CodeEditor?v=1.77~CodeEditorChat?v=0.28.js": "/vendors~CodeBox?v=0.43~CodeEditor?v=1.77~CodeEditorChat?v=0.28.js",
    "/ChatMessages?v=1.87.js": "/ChatMessages?v=1.87.js",
    "/Chats?v=7.11.js": "/Chats?v=7.11.js",
    "/vendors~CodeBox?v=0.43~CodeEditor?v=1.77.js": "/vendors~CodeBox?v=0.43~CodeEditor?v=1.77.js",
    "/CodeBox?v=0.44.js": "/CodeBox?v=0.44.js",
    "/vendors~CodeBox?v=0.44~CodeEditor?v=1.77.js": "/vendors~CodeBox?v=0.44~CodeEditor?v=1.77.js",
    "/vendors~CodeBox?v=0.44~CodeEditor?v=1.77~CodeEditorChat?v=0.28.js": "/vendors~CodeBox?v=0.44~CodeEditor?v=1.77~CodeEditorChat?v=0.28.js",
    "/ChatMessages?v=1.88.js": "/ChatMessages?v=1.88.js",
    "/Chats?v=7.12.js": "/Chats?v=7.12.js",
    "/CodeEditor?v=1.78.js": "/CodeEditor?v=1.78.js",
    "/vendors~CodeBox?v=0.44~CodeEditor?v=1.78.js": "/vendors~CodeBox?v=0.44~CodeEditor?v=1.78.js",
    "/vendors~CodeBox?v=0.44~CodeEditor?v=1.78~CodeEditorChat?v=0.28.js": "/vendors~CodeBox?v=0.44~CodeEditor?v=1.78~CodeEditorChat?v=0.28.js",
    "/Chats?v=7.13.js": "/Chats?v=7.13.js",
    "/vendors~CodeEditor?v=1.78.js": "/vendors~CodeEditor?v=1.78.js",
    "/CodeBox?v=0.45.js": "/CodeBox?v=0.45.js",
    "/vendors~CodeBox?v=0.45~CodeEditor?v=1.78~CodeEditorChat?v=0.28.js": "/vendors~CodeBox?v=0.45~CodeEditor?v=1.78~CodeEditorChat?v=0.28.js",
    "/ChatMessages?v=1.89.js": "/ChatMessages?v=1.89.js",
    "/CodeEditorChat?v=0.29.js": "/CodeEditorChat?v=0.29.js",
    "/vendors~CodeBox?v=0.45~CodeEditor?v=1.78~CodeEditorChat?v=0.29.js": "/vendors~CodeBox?v=0.45~CodeEditor?v=1.78~CodeEditorChat?v=0.29.js",
    "/Chats?v=7.14.js": "/Chats?v=7.14.js",
    "/CodeEditor?v=1.79.js": "/CodeEditor?v=1.79.js",
    "/vendors~CodeBox?v=0.45~CodeEditor?v=1.79~CodeEditorChat?v=0.29.js": "/vendors~CodeBox?v=0.45~CodeEditor?v=1.79~CodeEditorChat?v=0.29.js",
    "/CodeBox?v=0.46.js": "/CodeBox?v=0.46.js",
    "/vendors~CodeBox?v=0.46~CodeEditor?v=1.79~CodeEditorChat?v=0.29.js": "/vendors~CodeBox?v=0.46~CodeEditor?v=1.79~CodeEditorChat?v=0.29.js",
    "/ChatMessages?v=1.90.js": "/ChatMessages?v=1.90.js",
    "/CodeEditorChat?v=0.30.js": "/CodeEditorChat?v=0.30.js",
    "/vendors~CodeBox?v=0.46~CodeEditor?v=1.79~CodeEditorChat?v=0.30.js": "/vendors~CodeBox?v=0.46~CodeEditor?v=1.79~CodeEditorChat?v=0.30.js",
    "/Chats?v=7.15.js": "/Chats?v=7.15.js",
    "/CodeEditor?v=1.80.js": "/CodeEditor?v=1.80.js",
    "/vendors~CodeBox?v=0.46~CodeEditor?v=1.80~CodeEditorChat?v=0.30.js": "/vendors~CodeBox?v=0.46~CodeEditor?v=1.80~CodeEditorChat?v=0.30.js",
    "/Pets?v=0.21.js": "/Pets?v=0.21.js",
    "/PetList?v=0.10.js": "/PetList?v=0.10.js",
    "/PetList?v=0.11.js": "/PetList?v=0.11.js",
    "/Board?v=2.91.js": "/Board?v=2.91.js",
    "/Pets?v=0.10.js": "/Pets?v=0.10.js",
    "/PetList?v=0.12.js": "/PetList?v=0.12.js"
}
