{
    "/js/chunks/vendors~CodeBox~CodeEditor~CodeEditorChat.c56dff19f7bab57b1930.js": "/js/chunks/vendors~CodeBox~CodeEditor~CodeEditorChat.c56dff19f7bab57b1930.js",
    "/js/chunks/AudioPlayer.7d600cb01d0109eaea73.js": "/js/chunks/AudioPlayer.7d600cb01d0109eaea73.js",
    "/js/chunks/CodeBox.21a80e980f674b08a4c8.js": "/js/chunks/CodeBox.21a80e980f674b08a4c8.js",
    "/js/chunks/Images.d5cbde231da6d6dd2c63.js": "/js/chunks/Images.d5cbde231da6d6dd2c63.js",
    "/js/chunks/VideoPlayer.5a9eedd1f2907a770ecb.js": "/js/chunks/VideoPlayer.5a9eedd1f2907a770ecb.js",
    "/js/chunks/vendors~AddGem~PetContent.64c0cecd926849f8ddfc.js": "/js/chunks/vendors~AddGem~PetContent.64c0cecd926849f8ddfc.js",
    "/js/dashboard.js": "/js/dashboard.js",
    "/js/chunks/AddDatabase.05ddb08cef7f0b5d1511.js": "/js/chunks/AddDatabase.05ddb08cef7f0b5d1511.js",
    "/js/chunks/AddGem.c57920271c69b36f3c6e.js": "/js/chunks/AddGem.c57920271c69b36f3c6e.js",
    "/js/chunks/AddNewFile.40efeae51d332661e04c.js": "/js/chunks/AddNewFile.40efeae51d332661e04c.js",
    "/js/chunks/AddProject.540ae9d5370273c360b1.js": "/js/chunks/AddProject.540ae9d5370273c360b1.js",
    "/js/chunks/AddWebroute.0fff1efb71c6eb5efc66.js": "/js/chunks/AddWebroute.0fff1efb71c6eb5efc66.js",
    "/js/chunks/Board.011289268560ae90c996.js": "/js/chunks/Board.011289268560ae90c996.js",
    "/js/chunks/ChallengeDescription.88b305aca9e6bd2c5b11.js": "/js/chunks/ChallengeDescription.88b305aca9e6bd2c5b11.js",
    "/js/chunks/ChallengeDiscussions.95341808b3d52b189bf2.js": "/js/chunks/ChallengeDiscussions.95341808b3d52b189bf2.js",
    "/js/chunks/ChallengeJudges.b0dd2b00d939f6587d36.js": "/js/chunks/ChallengeJudges.b0dd2b00d939f6587d36.js",
    "/js/chunks/ChallengeLeaderboard.672b68d170f4250470f5.js": "/js/chunks/ChallengeLeaderboard.672b68d170f4250470f5.js",
    "/js/chunks/ChallengePanel.d7897e67d3efcddd9f96.js": "/js/chunks/ChallengePanel.d7897e67d3efcddd9f96.js",
    "/js/chunks/ChallengeRules.8cdac869711e26c44b1e.js": "/js/chunks/ChallengeRules.8cdac869711e26c44b1e.js",
    "/js/chunks/Challenges.45610f47720b5e713d84.js": "/js/chunks/Challenges.45610f47720b5e713d84.js",
    "/js/chunks/ChallengesCreate.6053228ab4ca2c6520e5.js": "/js/chunks/ChallengesCreate.6053228ab4ca2c6520e5.js",
    "/js/chunks/ChallengesList.a4e4e72b64808770746e.js": "/js/chunks/ChallengesList.a4e4e72b64808770746e.js",
    "/js/chunks/ChannelEdit.a583c66f8f9e9bd015be.js": "/js/chunks/ChannelEdit.a583c66f8f9e9bd015be.js",
    "/js/chunks/ChannelInfo.f09f1f08fdeb39147648.js": "/js/chunks/ChannelInfo.f09f1f08fdeb39147648.js",
    "/js/chunks/ChatBottom.e28bbbdf7066e3871f6d.js": "/js/chunks/ChatBottom.e28bbbdf7066e3871f6d.js",
    "/js/chunks/ChatList.b3aa26d02edb39481361.js": "/js/chunks/ChatList.b3aa26d02edb39481361.js",
    "/js/chunks/ChatMessages.ce86c88d830e1e2d478a.js": "/js/chunks/ChatMessages.ce86c88d830e1e2d478a.js",
    "/js/chunks/ChatTop.202d5b38336a0b38b62e.js": "/js/chunks/ChatTop.202d5b38336a0b38b62e.js",
    "/js/chunks/Chats.b57d8b2f72fa6a5c2dd6.js": "/js/chunks/Chats.b57d8b2f72fa6a5c2dd6.js",
    "/js/chunks/CodeEditor.5f1e3a46ee25063bbcb9.js": "/js/chunks/CodeEditor.5f1e3a46ee25063bbcb9.js",
    "/js/chunks/CodeEditorChat.bbd919b448c7df8fc299.js": "/js/chunks/CodeEditorChat.bbd919b448c7df8fc299.js",
    "/js/chunks/CreateChannel.d9107552a6a14540c3a4.js": "/js/chunks/CreateChannel.d9107552a6a14540c3a4.js",
    "/js/chunks/EditProfile.bab16f1e26a181037bb9.js": "/js/chunks/EditProfile.bab16f1e26a181037bb9.js",
    "/js/chunks/ForgotPassword.ad1c0d1a4cbeaaa429c3.js": "/js/chunks/ForgotPassword.ad1c0d1a4cbeaaa429c3.js",
    "/js/chunks/GetPet.fb7660d2dd77a2516843.js": "/js/chunks/GetPet.fb7660d2dd77a2516843.js",
    "/js/chunks/Hub.9c8c646728e995d9ca2b.js": "/js/chunks/Hub.9c8c646728e995d9ca2b.js",
    "/js/chunks/ImageLoader?v=0.10.fbb6f8b8f06fc4441e75.js": "/js/chunks/ImageLoader?v=0.10.fbb6f8b8f06fc4441e75.js",
    "/js/chunks/ImageViewer.ca0b3e5d9a273264f457.js": "/js/chunks/ImageViewer.ca0b3e5d9a273264f457.js",
    "/js/chunks/LiveSession.9b1c96f80b076243fac0.js": "/js/chunks/LiveSession.9b1c96f80b076243fac0.js",
    "/js/chunks/PanelLoader.98192bd955de62c0e6bc.js": "/js/chunks/PanelLoader.98192bd955de62c0e6bc.js",
    "/js/chunks/PanelSettings.f98b4740efdc630fc515.js": "/js/chunks/PanelSettings.f98b4740efdc630fc515.js",
    "/js/chunks/PetBoard.c92db8c8f008748708f4.js": "/js/chunks/PetBoard.c92db8c8f008748708f4.js",
    "/js/chunks/PetContent.b4c047533e7afff9c1cc.js": "/js/chunks/PetContent.b4c047533e7afff9c1cc.js",
    "/js/chunks/PetList.03d69e7fb015df5c578c.js": "/js/chunks/PetList.03d69e7fb015df5c578c.js",
    "/js/chunks/Pets.2f5533501f1f639ec2cd.js": "/js/chunks/Pets.2f5533501f1f639ec2cd.js",
    "/js/chunks/ProfilePage.cc33dc0624e2042e483b.js": "/js/chunks/ProfilePage.cc33dc0624e2042e483b.js",
    "/js/chunks/ProjectList.6134be067241b0da1771.js": "/js/chunks/ProjectList.6134be067241b0da1771.js",
    "/js/chunks/ProjectPanel.3bfb45cba40fdb426985.js": "/js/chunks/ProjectPanel.3bfb45cba40fdb426985.js",
    "/js/chunks/ProjectView.abd4c6016313e3f03d99.js": "/js/chunks/ProjectView.abd4c6016313e3f03d99.js",
    "/js/chunks/Projects.22ab0d3eda7d55c3b5c9.js": "/js/chunks/Projects.22ab0d3eda7d55c3b5c9.js",
    "/js/chunks/ResetPassword.bc9b5c1d2fb720a7e0a2.js": "/js/chunks/ResetPassword.bc9b5c1d2fb720a7e0a2.js",
    "/js/chunks/ResourceUpload.5c4ad57d9822be5ac734.js": "/js/chunks/ResourceUpload.5c4ad57d9822be5ac734.js",
    "/js/chunks/SetUsername.ef8a77ea0ea3c6fb4540.js": "/js/chunks/SetUsername.ef8a77ea0ea3c6fb4540.js",
    "/js/chunks/SubChannels.1896a0d6ddb95d6844cf.js": "/js/chunks/SubChannels.1896a0d6ddb95d6844cf.js",
    "/js/chunks/VPressEditor?v=0.12.58029ddc3a278f1f6832.js": "/js/chunks/VPressEditor?v=0.12.58029ddc3a278f1f6832.js",
    "/js/chunks/addPage.491ca62bc3bda79b3366.js": "/js/chunks/addPage.491ca62bc3bda79b3366.js",
    "/js/chunks/login.119045c6604c4ed200f2.js": "/js/chunks/login.119045c6604c4ed200f2.js",
    "/js/chunks/panel-side.f2f24aeee62af6087f15.js": "/js/chunks/panel-side.f2f24aeee62af6087f15.js",
    "/js/chunks/register.312cdc0377e3086c3480.js": "/js/chunks/register.312cdc0377e3086c3480.js",
    "/js/chunks/top-bar.eb4db9103f22c5793589.js": "/js/chunks/top-bar.eb4db9103f22c5793589.js",
    "/js/chunks/top-bar-chat.ebae711ce6cea6a7e27d.js": "/js/chunks/top-bar-chat.ebae711ce6cea6a7e27d.js",
    "/js/chunks/top-bar-profile.ac18bf38037ddf5557b7.js": "/js/chunks/top-bar-profile.ac18bf38037ddf5557b7.js",
    "/js/chunks/vendors~VPressEditor?v=0.12.0d56e4234aa9cd21dff5.js": "/js/chunks/vendors~VPressEditor?v=0.12.0d56e4234aa9cd21dff5.js",
    "/js/chunks/verify.a9f0603efe202dd9a402.js": "/js/chunks/verify.a9f0603efe202dd9a402.js"
}
