{
    "/js/chunks/vendors~AddGem~AddProject~ChallengePanel~ChallengesCreate~Chats~DiaryBoard~FeedForm~ForgotPassword~G~00bea193.b4d5c405129468694bbb.js": "/js/chunks/vendors~AddGem~AddProject~ChallengePanel~ChallengesCreate~Chats~DiaryBoard~FeedForm~ForgotPassword~G~00bea193.b4d5c405129468694bbb.js",
    "/js/chunks/vendors~AddGem~CodeBox~CodeEditor~CodeEditorChat.1c15f4443626560de208.js": "/js/chunks/vendors~AddGem~CodeBox~CodeEditor~CodeEditorChat.1c15f4443626560de208.js",
    "/js/chunks/vendors~ChallengesList~Chats~ProjectView.6b850b433da1f090b8ff.js": "/js/chunks/vendors~ChallengesList~Chats~ProjectView.6b850b433da1f090b8ff.js",
    "/js/chunks/AudioPlayer.6c99ae25b0824db5af63.js": "/js/chunks/AudioPlayer.6c99ae25b0824db5af63.js",
    "/js/chunks/Images.686bb7b8f79557c8db7b.js": "/js/chunks/Images.686bb7b8f79557c8db7b.js",
    "/js/chunks/ProfilePage.dee540dd38ce7b33bc13.js": "/js/chunks/ProfilePage.dee540dd38ce7b33bc13.js",
    "/js/chunks/VideoPlayer.fadb374c2830150f0c56.js": "/js/chunks/VideoPlayer.fadb374c2830150f0c56.js",
    "/js/chunks/vendors~AddGem~DiaryContent.1b99698116907cc298be.js": "/js/chunks/vendors~AddGem~DiaryContent.1b99698116907cc298be.js",
    "/js/chunks/vendors~CodeEditor~CodeEditorChat.7ee538aef305ad43d53d.js": "/js/chunks/vendors~CodeEditor~CodeEditorChat.7ee538aef305ad43d53d.js",
    "/js/chunks/vendors~CodeEditor~InputHandler.5ac8f0c50ce352b88de7.js": "/js/chunks/vendors~CodeEditor~InputHandler.5ac8f0c50ce352b88de7.js",
    "/js/app.js": "/js/app.js",
    "/js/dashboard.js": "/js/dashboard.js",
    "/js/chunks/AddDatabase.d7a7135dade597135f66.js": "/js/chunks/AddDatabase.d7a7135dade597135f66.js",
    "/js/chunks/AddGem.60e706ae41d1b57d94e2.js": "/js/chunks/AddGem.60e706ae41d1b57d94e2.js",
    "/js/chunks/AddGit.d0dbd6096747ef5bead9.js": "/js/chunks/AddGit.d0dbd6096747ef5bead9.js",
    "/js/chunks/AddNewFile.1dea12c50ad26d0ed6cc.js": "/js/chunks/AddNewFile.1dea12c50ad26d0ed6cc.js",
    "/js/chunks/AddPayment.88c114b57742045dd1dc.js": "/js/chunks/AddPayment.88c114b57742045dd1dc.js",
    "/js/chunks/AddProject.6cddfd103bb434f446a4.js": "/js/chunks/AddProject.6cddfd103bb434f446a4.js",
    "/js/chunks/AddSubChannel.defcf4e48858e6fcc2f0.js": "/js/chunks/AddSubChannel.defcf4e48858e6fcc2f0.js",
    "/js/chunks/AddWebroute.4f49e1f376b7abf81098.js": "/js/chunks/AddWebroute.4f49e1f376b7abf81098.js",
    "/js/chunks/BalanceInfo.e4fc137002939a5aebad.js": "/js/chunks/BalanceInfo.e4fc137002939a5aebad.js",
    "/js/chunks/Board.76ac8069ba6b2dff8df9.js": "/js/chunks/Board.76ac8069ba6b2dff8df9.js",
    "/js/chunks/Challenge.8dbd1cc7688ec661f375.js": "/js/chunks/Challenge.8dbd1cc7688ec661f375.js",
    "/js/chunks/ChallengeDescription.ad9933ae18045938dd74.js": "/js/chunks/ChallengeDescription.ad9933ae18045938dd74.js",
    "/js/chunks/ChallengeDiscussions.dae2b104db43e28b4c3d.js": "/js/chunks/ChallengeDiscussions.dae2b104db43e28b4c3d.js",
    "/js/chunks/ChallengeJudges.2a0392e0284249c71373.js": "/js/chunks/ChallengeJudges.2a0392e0284249c71373.js",
    "/js/chunks/ChallengeLeaderboard.e7f9c4553184c22fe671.js": "/js/chunks/ChallengeLeaderboard.e7f9c4553184c22fe671.js",
    "/js/chunks/ChallengePanel.3c3d3a10f503732eeea8.js": "/js/chunks/ChallengePanel.3c3d3a10f503732eeea8.js",
    "/js/chunks/ChallengeResult.49ca4f7a83fbcf4ab3fe.js": "/js/chunks/ChallengeResult.49ca4f7a83fbcf4ab3fe.js",
    "/js/chunks/ChallengeRules.e586d7f88c0435e76c9a.js": "/js/chunks/ChallengeRules.e586d7f88c0435e76c9a.js",
    "/js/chunks/Challenges.88f8257c65a68ab54e6a.js": "/js/chunks/Challenges.88f8257c65a68ab54e6a.js",
    "/js/chunks/ChallengesCreate.c636b4d3962b641c0eb8.js": "/js/chunks/ChallengesCreate.c636b4d3962b641c0eb8.js",
    "/js/chunks/ChallengesList.30207534fdbcf745a013.js": "/js/chunks/ChallengesList.30207534fdbcf745a013.js",
    "/js/chunks/ChannelEdit.c2dfd652cbbd2c8cd246.js": "/js/chunks/ChannelEdit.c2dfd652cbbd2c8cd246.js",
    "/js/chunks/ChannelInfo.41e9e8d190c2505620e2.js": "/js/chunks/ChannelInfo.41e9e8d190c2505620e2.js",
    "/js/chunks/ChatBottom.24e967f2dfe05177a6e0.js": "/js/chunks/ChatBottom.24e967f2dfe05177a6e0.js",
    "/js/chunks/ChatList.87e266f1eb2848354300.js": "/js/chunks/ChatList.87e266f1eb2848354300.js",
    "/js/chunks/ChatMessages.56ccb61ccb973eb4c9a7.js": "/js/chunks/ChatMessages.56ccb61ccb973eb4c9a7.js",
    "/js/chunks/ChatShare.0ee1241cefdd715082aa.js": "/js/chunks/ChatShare.0ee1241cefdd715082aa.js",
    "/js/chunks/ChatTop.fab18bf62ee0a03cd452.js": "/js/chunks/ChatTop.fab18bf62ee0a03cd452.js",
    "/js/chunks/Chats.53d51ab41169267a385e.js": "/js/chunks/Chats.53d51ab41169267a385e.js",
    "/js/chunks/CodeBox.4eb41a824c89a1e83855.js": "/js/chunks/CodeBox.4eb41a824c89a1e83855.js",
    "/js/chunks/CodeBox?v=0.53.d5d26e2200cf3939800e.js": "/js/chunks/CodeBox?v=0.53.d5d26e2200cf3939800e.js",
    "/js/chunks/CodeEditor.fc575539f778b8d5750b.js": "/js/chunks/CodeEditor.fc575539f778b8d5750b.js",
    "/js/chunks/CodeEditorChat.48ad6c37450d634ecdef.js": "/js/chunks/CodeEditorChat.48ad6c37450d634ecdef.js",
    "/js/chunks/CommentPost.6d77c0d0bfa617bc1237.js": "/js/chunks/CommentPost.6d77c0d0bfa617bc1237.js",
    "/js/chunks/CreateChannel.2575273fbd00f52c3bce.js": "/js/chunks/CreateChannel.2575273fbd00f52c3bce.js",
    "/js/chunks/Diary.ee199ad5883a61bfea95.js": "/js/chunks/Diary.ee199ad5883a61bfea95.js",
    "/js/chunks/DiaryBank.dac145f942a4c9783e5e.js": "/js/chunks/DiaryBank.dac145f942a4c9783e5e.js",
    "/js/chunks/DiaryBoard.5173d69f596429f8ccfa.js": "/js/chunks/DiaryBoard.5173d69f596429f8ccfa.js",
    "/js/chunks/DiaryContent.ae73877764f61bcca8a4.js": "/js/chunks/DiaryContent.ae73877764f61bcca8a4.js",
    "/js/chunks/DiaryList.3d316f177cf7ef8a181a.js": "/js/chunks/DiaryList.3d316f177cf7ef8a181a.js",
    "/js/chunks/DiaryNotes.1e98b13f1774a025058f.js": "/js/chunks/DiaryNotes.1e98b13f1774a025058f.js",
    "/js/chunks/EachProject.4c189faac18cd7704d5a.js": "/js/chunks/EachProject.4c189faac18cd7704d5a.js",
    "/js/chunks/EditProfile.0b488e9de170517f3760.js": "/js/chunks/EditProfile.0b488e9de170517f3760.js",
    "/js/chunks/FeeInfo.f37f3bdc2ad01a9640e3.js": "/js/chunks/FeeInfo.f37f3bdc2ad01a9640e3.js",
    "/js/chunks/FeedForm.36b6e57c92831f0a7ce2.js": "/js/chunks/FeedForm.36b6e57c92831f0a7ce2.js",
    "/js/chunks/Feedback.9559ab8b9d0b9b1fbe28.js": "/js/chunks/Feedback.9559ab8b9d0b9b1fbe28.js",
    "/js/chunks/Follow.9d5a8c36214efb715427.js": "/js/chunks/Follow.9d5a8c36214efb715427.js",
    "/js/chunks/ForgotPassword.dbde6c89dd879872b266.js": "/js/chunks/ForgotPassword.dbde6c89dd879872b266.js",
    "/js/chunks/GetDiary.4bc794a5f589a0216041.js": "/js/chunks/GetDiary.4bc794a5f589a0216041.js",
    "/js/chunks/Hub.7520492394f45fb2942f.js": "/js/chunks/Hub.7520492394f45fb2942f.js",
    "/js/chunks/ImageCropper.065c41d43a950dcb5c1c.js": "/js/chunks/ImageCropper.065c41d43a950dcb5c1c.js",
    "/js/chunks/ImageCropperMain.54d5800c0ad385e72599.js": "/js/chunks/ImageCropperMain.54d5800c0ad385e72599.js",
    "/js/chunks/ImageLoader.514d3c0e7b0f64ce231f.js": "/js/chunks/ImageLoader.514d3c0e7b0f64ce231f.js",
    "/js/chunks/ImageLoader?v=0.10.6ad1b38ef6c316556ce4.js": "/js/chunks/ImageLoader?v=0.10.6ad1b38ef6c316556ce4.js",
    "/js/chunks/ImageViewer.ddb4ad5aa0b6f27aa5b0.js": "/js/chunks/ImageViewer.ddb4ad5aa0b6f27aa5b0.js",
    "/js/chunks/InputHandler.1a20abb01b045d60184c.js": "/js/chunks/InputHandler.1a20abb01b045d60184c.js",
    "/js/chunks/Interest.5f56b0813ff5916b5ed1.js": "/js/chunks/Interest.5f56b0813ff5916b5ed1.js",
    "/js/chunks/Invitation.f3c40f3a49ba2507db3e.js": "/js/chunks/Invitation.f3c40f3a49ba2507db3e.js",
    "/js/chunks/LiveSession.fc8581f3062da51d050d.js": "/js/chunks/LiveSession.fc8581f3062da51d050d.js",
    "/js/chunks/MentorInfo.da470bf114ac94e15f83.js": "/js/chunks/MentorInfo.da470bf114ac94e15f83.js",
    "/js/chunks/Mentors.bd5dcaa41b1f7f3b3b39.js": "/js/chunks/Mentors.bd5dcaa41b1f7f3b3b39.js",
    "/js/chunks/MentorsList.5dcad76399cbb4500c71.js": "/js/chunks/MentorsList.5dcad76399cbb4500c71.js",
    "/js/chunks/MoreOptionChat.0aadc943c8d133edb980.js": "/js/chunks/MoreOptionChat.0aadc943c8d133edb980.js",
    "/js/chunks/MoreOptions.3ef469d504a4c190672c.js": "/js/chunks/MoreOptions.3ef469d504a4c190672c.js",
    "/js/chunks/MoreOptionsPanel.9536a4a98de2cc992d38.js": "/js/chunks/MoreOptionsPanel.9536a4a98de2cc992d38.js",
    "/js/chunks/MoreOptionsPost.61fa08ff86fef9db4b63.js": "/js/chunks/MoreOptionsPost.61fa08ff86fef9db4b63.js",
    "/js/chunks/Notifications.9a018b91f14fe966d51a.js": "/js/chunks/Notifications.9a018b91f14fe966d51a.js",
    "/js/chunks/NotificationsList.0ef2900bbf661ea78880.js": "/js/chunks/NotificationsList.0ef2900bbf661ea78880.js",
    "/js/chunks/Notify.13a7032a44aa890f68e5.js": "/js/chunks/Notify.13a7032a44aa890f68e5.js",
    "/js/chunks/PanelLoader.8b5ddbc163eb0bbac254.js": "/js/chunks/PanelLoader.8b5ddbc163eb0bbac254.js",
    "/js/chunks/PanelLoaderChallenge.a35ea2540b52276ed64d.js": "/js/chunks/PanelLoaderChallenge.a35ea2540b52276ed64d.js",
    "/js/chunks/PanelSettings.cdc04e6e7c28313ed219.js": "/js/chunks/PanelSettings.cdc04e6e7c28313ed219.js",
    "/js/chunks/PaymentInfoBoard.780a798a9b8969059156.js": "/js/chunks/PaymentInfoBoard.780a798a9b8969059156.js",
    "/js/chunks/PaymentProcessor.15819a615f7164aa24e4.js": "/js/chunks/PaymentProcessor.15819a615f7164aa24e4.js",
    "/js/chunks/PayoutInfo.b0c2596e8566d7cd54f5.js": "/js/chunks/PayoutInfo.b0c2596e8566d7cd54f5.js",
    "/js/chunks/PointInfoBoard.b923e7aea8fd1fed2f14.js": "/js/chunks/PointInfoBoard.b923e7aea8fd1fed2f14.js",
    "/js/chunks/PostView.7ed2643c65e15d8a0386.js": "/js/chunks/PostView.7ed2643c65e15d8a0386.js",
    "/js/chunks/ProjectGuide.3a942b76f18a56a17671.js": "/js/chunks/ProjectGuide.3a942b76f18a56a17671.js",
    "/js/chunks/ProjectList.c439f7d81f277bba9710.js": "/js/chunks/ProjectList.c439f7d81f277bba9710.js",
    "/js/chunks/ProjectPanel.c748600ada9fb32a9d08.js": "/js/chunks/ProjectPanel.c748600ada9fb32a9d08.js",
    "/js/chunks/ProjectView.81674bfb0e9006a67642.js": "/js/chunks/ProjectView.81674bfb0e9006a67642.js",
    "/js/chunks/Projects.85d38f80394e3994ba8b.js": "/js/chunks/Projects.85d38f80394e3994ba8b.js",
    "/js/chunks/ReferralInfo.c061a3c0dd970830437c.js": "/js/chunks/ReferralInfo.c061a3c0dd970830437c.js",
    "/js/chunks/ReplyView.5c4bf503aac4bde989d4.js": "/js/chunks/ReplyView.5c4bf503aac4bde989d4.js",
    "/js/chunks/ResetPassword.26bd35a38a8031042576.js": "/js/chunks/ResetPassword.26bd35a38a8031042576.js",
    "/js/chunks/ResourceUpload.0c4dbc7ae0df60f3ddae.js": "/js/chunks/ResourceUpload.0c4dbc7ae0df60f3ddae.js",
    "/js/chunks/Reward.edf771f342c3eec5a511.js": "/js/chunks/Reward.edf771f342c3eec5a511.js",
    "/js/chunks/SetUsername.185bcf215ce69a4cf018.js": "/js/chunks/SetUsername.185bcf215ce69a4cf018.js",
    "/js/chunks/Settings.322ffe4302c6c15a5559.js": "/js/chunks/Settings.322ffe4302c6c15a5559.js",
    "/js/chunks/SettingsMain.06428b95d9e1f46c70e4.js": "/js/chunks/SettingsMain.06428b95d9e1f46c70e4.js",
    "/js/chunks/SideBar.386df2c97dc8f7ae080e.js": "/js/chunks/SideBar.386df2c97dc8f7ae080e.js",
    "/js/chunks/SubChannels.97f867f9c63ed24aa5cf.js": "/js/chunks/SubChannels.97f867f9c63ed24aa5cf.js",
    "/js/chunks/TopBarBoard.605b84067df3b3a64594.js": "/js/chunks/TopBarBoard.605b84067df3b3a64594.js",
    "/js/chunks/TransactionInfo.d927817618ddb35de79f.js": "/js/chunks/TransactionInfo.d927817618ddb35de79f.js",
    "/js/chunks/VPressEditor.47e61b153b229a277eb9.js": "/js/chunks/VPressEditor.47e61b153b229a277eb9.js",
    "/js/chunks/Wallet.ad22c1b9b6534fb67c05.js": "/js/chunks/Wallet.ad22c1b9b6534fb67c05.js",
    "/js/chunks/WalletCard.14ca9e93827502d763d4.js": "/js/chunks/WalletCard.14ca9e93827502d763d4.js",
    "/js/chunks/WalletInfo.1dd11030d5e09a0d258d.js": "/js/chunks/WalletInfo.1dd11030d5e09a0d258d.js",
    "/js/chunks/addPage.4dbd085ebe098a873faf.js": "/js/chunks/addPage.4dbd085ebe098a873faf.js",
    "/js/chunks/imageCropperBoard.e043956dae5b459a9129.js": "/js/chunks/imageCropperBoard.e043956dae5b459a9129.js",
    "/js/chunks/imageCropperBoardDiary.4a4074ddbc5e50ade426.js": "/js/chunks/imageCropperBoardDiary.4a4074ddbc5e50ade426.js",
    "/js/chunks/login.c15e4a389f68a85036cd.js": "/js/chunks/login.c15e4a389f68a85036cd.js",
    "/js/chunks/manageWallet.d143a8834bf41b220ac5.js": "/js/chunks/manageWallet.d143a8834bf41b220ac5.js",
    "/js/chunks/panel-side.28433dcb2a787815783d.js": "/js/chunks/panel-side.28433dcb2a787815783d.js",
    "/js/chunks/register.3f4e9c27d4e890c0d6d7.js": "/js/chunks/register.3f4e9c27d4e890c0d6d7.js",
    "/js/chunks/top-bar.940c56b1fcaf616c523f.js": "/js/chunks/top-bar.940c56b1fcaf616c523f.js",
    "/js/chunks/top-bar-chat.3b843257f851a62c8f67.js": "/js/chunks/top-bar-chat.3b843257f851a62c8f67.js",
    "/js/chunks/top-bar-profile.df283f159564960f3b2b.js": "/js/chunks/top-bar-profile.df283f159564960f3b2b.js",
    "/js/chunks/vendors~Chats.8694a43784b6f340ff84.js": "/js/chunks/vendors~Chats.8694a43784b6f340ff84.js",
    "/js/chunks/vendors~Hub.17b6f3acd2695564585f.js": "/js/chunks/vendors~Hub.17b6f3acd2695564585f.js",
    "/js/chunks/vendors~ImageCropperMain.f0a59a4ea5cd4eb346b3.js": "/js/chunks/vendors~ImageCropperMain.f0a59a4ea5cd4eb346b3.js",
    "/js/chunks/vendors~VPressEditor.8c76f200da7367be4b9e.js": "/js/chunks/vendors~VPressEditor.8c76f200da7367be4b9e.js",
    "/js/chunks/verify.1c0a780653f66c14d590.js": "/js/chunks/verify.1c0a780653f66c14d590.js"
}
